chbe444umd/HENDesign.py
chbe444umd/ReactionSystem.py
chbe444umd/Reactors.py
chbe444umd/Stream.py
chbe444umd/TernarySystem.py
chbe444umd/__init__.py
chbe444umd/desmos.py
chbe444umd/figures.py
chbe444umd/simplex.py
chbe444umd/synheat.py
chbe444umd-1.8.0.dist-info/METADATA
chbe444umd-1.8.0.dist-info/WHEEL
chbe444umd-1.8.0.dist-info/entry_points.txt
chbe444umd-1.8.0.dist-info/top_level.txt
chbe444umd-1.8.0.dist-info/RECORD
