Metadata-Version: 2.4
Name: chbe444umd
Version: 1.8.0
Summary: Python Repository for CHBE444: ChE Design I, University of Maryland, maintained by Ganesh Sriram
Author-email: Ganesh Sriram <gsriram@umd.edu>
Project-URL: Homepage, https://github.com/gsriramlab-umd/chbe444umd
Project-URL: Issues, https://github.com/gsriramlab-umd/chbe444umd/issues
Keywords: chbe444,design,che design,lp,simplex
Classifier: Programming Language :: Python :: 3
Classifier: Operating System :: OS Independent
Requires-Python: >=3.10
Provides-Extra: dev
Requires-Dist: pytest; extra == "dev"
Requires-Dist: build; extra == "dev"
Requires-Dist: twine; extra == "dev"
